cartooner/__init__.py
cartooner/cartooner.py
cartoonizer/__init__.py
cartoonizer/cartoonizer.py
cartooner-0.0.2.dist-info/LICENSE
cartooner-0.0.2.dist-info/METADATA
cartooner-0.0.2.dist-info/WHEEL
cartooner-0.0.2.dist-info/top_level.txt
cartooner-0.0.2.dist-info/RECORD
