Metadata-Version: 2.1
Name: cartooner
Version: 0.0.2
Summary: This tool converts your photo into a cartoon-like image
Home-page: https://github.com/lutianming/cartoonizer
Author: Tianming LU
Author-email: tianming.lu@foxmail.com
License: UNKNOWN
Platform: UNKNOWN
Classifier: Programming Language :: Python :: 3
Classifier: License :: OSI Approved :: MIT License
Classifier: Operating System :: OS Independent
Requires-Python: >=3.6
Requires-Dist: numpy
Requires-Dist: scipy
Requires-Dist: opencv-python
